{
  "schema": "component-manifest/v1",
  "components": [
    {
      "name": "libtls",
      "version": "3.9.0",
      "description": "LibreSSL Portable itself. This includes the build scaffold and compatibility layer that builds portable LibreSSL from the OpenBSD source code. Pull requests or patches sent to tech@openbsd.org are welcome.",
      "license": {
        "expression": "ISC"
      },
      "purl": "pkg:github/libressl/portable@3.9.0",
      "external_references": [
        {
          "type": "website",
          "url": "https://www.libressl.org"
        },
        {
          "type": "vcs",
          "url": "https://github.com/libressl/portable"
        },
        {
          "type": "issue-tracker",
          "url": "https://github.com/libressl/portable/issues"
        }
      ],
      "tags": [
        "core"
      ]
    },
    {
      "name": "lvgl",
      "version": "v9.2.2",
      "description": "Embedded graphics library to create beautiful UIs for any MCU, MPU and display type. ",
      "license": {
        "expression": "MIT"
      },
      "purl": "pkg:github/lvgl/lvgl@v9.2.2",
      "external_references": [
        {
          "type": "website",
          "url": "https://lvgl.io"
        },
        {
          "type": "vcs",
          "url": "https://github.com/lvgl/lvgl"
        },
        {
          "type": "issue-tracker",
          "url": "https://github.com/lvgl/lvgl/issues"
        }
      ],
      "tags": [
        "display"
      ]
    }
  ]
}
